agentask/__init__.py
agentask/calendar_generator.py
agentask/calendar_main.py
agentask/cli.py
agentask/ocr.py
agentask/plan_main.py
agentask/planner.py
agentask/summary.py
agentask/understand_main.py
agentask/utils.py
agentask/visual.py
agentask/wrapper.py
agentask-0.1.3.dist-info/METADATA
agentask-0.1.3.dist-info/WHEEL
agentask-0.1.3.dist-info/entry_points.txt
agentask-0.1.3.dist-info/top_level.txt
agentask-0.1.3.dist-info/RECORD
