Metadata-Version: 2.4
Name: agentask
Version: 0.1.3
Summary: An AI-powered task planning assistant with calendar generation
Home-page: https://github.com/yourusername/taskflow
Author: TaskFlow Team
Author-email: example@example.com
Classifier: Programming Language :: Python :: 3
Classifier: License :: OSI Approved :: MIT License
Classifier: Operating System :: OS Independent
Requires-Python: >=3.8
Requires-Dist: mistralai
Requires-Dist: google-generativeai
Requires-Dist: python-dotenv
Requires-Dist: icalendar
Requires-Dist: grpcio==1.60.1
Dynamic: author
Dynamic: author-email
Dynamic: classifier
Dynamic: description
Dynamic: description-content-type
Dynamic: home-page
Dynamic: requires-dist
Dynamic: requires-python
Dynamic: summary
